naeural_core/__init__.py
naeural_core/constants.py
naeural_core/data_structures.py
naeural_core/decentrai_object.py
naeural_core/manager.py
naeural_core/bc/__init__.py
naeural_core/business/__init__.py
naeural_core/business/business_manager.py
naeural_core/business/utils.py
naeural_core/business/base/__init__.py
naeural_core/business/base/base_plugin_biz.py
naeural_core/business/base/base_plugin_biz_api.py
naeural_core/business/base/base_plugin_biz_loop.py
naeural_core/business/base/cv_plugin_executor.py
naeural_core/business/base/network_processor.py
naeural_core/business/base/sd_plugin_executor.py
naeural_core/business/base/simple_rest_executor.py
naeural_core/business/base/drivers/__init__.py
naeural_core/business/base/drivers/device.py
naeural_core/business/base/drivers/external_program_device.py
naeural_core/business/base/drivers/http_device.py
naeural_core/business/base/drivers/utils/json_util.py
naeural_core/business/base/uvicorn_templates/basic_server.j2
naeural_core/business/base/web_app/__init__.py
naeural_core/business/base/web_app/base_tunnel_engine_plugin.py
naeural_core/business/base/web_app/base_web_app_plugin.py
naeural_core/business/default/code_executor.py
naeural_core/business/default/custom_exec_01.py
naeural_core/business/default/iot_listener_01.py
naeural_core/business/default/object_detector.py
naeural_core/business/default/rest_custom_exec_01.py
naeural_core/business/default/admin/chain_store_base.py
naeural_core/business/default/admin/k8s_monitor_01.py
naeural_core/business/default/admin/local_comms_01.py
naeural_core/business/default/admin/minio_monit_01.py
naeural_core/business/default/admin/net_config_monitor.py
naeural_core/business/default/admin/net_mon_01.py
naeural_core/business/default/admin/plugin_monitor_01.py
naeural_core/business/default/admin/self_check_01.py
naeural_core/business/default/admin/system_health_monitor_01.py
naeural_core/business/default/admin/update_monitor_01.py
naeural_core-7.7.240.dist-info/METADATA
naeural_core-7.7.240.dist-info/WHEEL
naeural_core-7.7.240.dist-info/licenses/LICENSE
naeural_core-7.7.240.dist-info/RECORD
