Metadata-Version: 2.4
Name: naeural_core
Version: 7.7.240
Summary: Ratio1 Core is the backbone of the Ratio1 Edge Protocol.
Project-URL: Homepage, https://github.com/Ratio1/naeural_core
Project-URL: Bug Tracker, https://github.com/Ratio1/naeural_core/issues
Author-email: Andrei Ionut Damian <andrei.damian@me.com>, Cristan Bleotiu <cristibleotiu@gmail.com>
License-File: LICENSE
Classifier: License :: OSI Approved :: MIT License
Classifier: Operating System :: OS Independent
Classifier: Programming Language :: Python :: 3
Requires-Python: >=3.10
Requires-Dist: bs4
Requires-Dist: cryptography==42.0.7
Requires-Dist: decentra-vision
Requires-Dist: decord
Requires-Dist: dropbox
Requires-Dist: fastapi
Requires-Dist: gql
Requires-Dist: h5py
Requires-Dist: minio
Requires-Dist: opencv-python-headless
Requires-Dist: paho-mqtt>=1.6
Requires-Dist: pandas
Requires-Dist: pika>=1.3
Requires-Dist: pyarrow>=15
Requires-Dist: pydantic
Requires-Dist: pymssql
Requires-Dist: pynvml>=11.4
Requires-Dist: pyyaml>=6.0
Requires-Dist: ratio1>=1.0.0
Requires-Dist: scikit-image
Requires-Dist: scikit-learn
Requires-Dist: seaborn
Requires-Dist: sentencepiece
Requires-Dist: shapely
Requires-Dist: tokenizers>=0.14.1
Requires-Dist: torch
Requires-Dist: torchaudio
Requires-Dist: torchvision
Requires-Dist: transformers>=4.38.0
Requires-Dist: unidecode
Requires-Dist: uvicorn
Requires-Dist: web3
